CVAT/__init__.py
CVAT/_delete.py
CVAT/_get.py
CVAT/_patch.py
CVAT/_post.py
CVAT/_put.py
CVAT/_static.py
CVAT/data_types.py
CVAT/utils.py
CVAT/Predictions/Foodvisor.py
CVAT/Predictions/Interface.py
CVAT/Predictions/__init__.py
CVAT_wrapper-1.0.0.dist-info/LICENSE
CVAT_wrapper-1.0.0.dist-info/METADATA
CVAT_wrapper-1.0.0.dist-info/WHEEL
CVAT_wrapper-1.0.0.dist-info/top_level.txt
CVAT_wrapper-1.0.0.dist-info/RECORD
